jqpy.py
jqpy-1.0.0.dist-info/WHEEL
jqpy-1.0.0.dist-info/METADATA
jqpy-1.0.0.dist-info/RECORD
