Metadata-Version: 2.1
Name: jqpy
Version: 1.0.0
Summary: JQpy is Python binding for JQ (JSON processing language) that simply works on any platform (even Windows) and does not require compilation.
Keywords: jq,json,query,binding,processor
Author-email: baterflyrity <baterflyrity@yandex.ru>
Project-URL: Documentation, https://baterflyrity.github.io/jqpy
Project-URL: Source, https://github.com/baterflyrity/jqpy
